MANIFEST.in
setup.py
b2gperf/__init__.py
b2gperf/b2gperf.py
b2gperf/kill.py
b2gperf/launchapp.js
b2gperf/listapps.py
b2gperf/mozperf.py
b2gperf/scrollapp.js
b2gperf/simple_launch.py
b2gperf/version.py
b2gperf_v1.4.egg-info/PKG-INFO
b2gperf_v1.4.egg-info/SOURCES.txt
b2gperf_v1.4.egg-info/dependency_links.txt
b2gperf_v1.4.egg-info/entry_points.txt
b2gperf_v1.4.egg-info/not-zip-safe
b2gperf_v1.4.egg-info/requires.txt
b2gperf_v1.4.egg-info/top_level.txt